{"topBlock": {"sites": {"total": 23, "govt": 23, "pvt": 0, "today": null}, "sessions": {"total": 3650, "govt": 3650, "pvt": 0, "today": null}, "registration": {"total": null, "male": null, "female": null, "others": null, "today": null}, "vaccination": {"total": 39179, "male": 25229, "female": 13950, "others": 0, "covishield": 32098, "covaxin": 7080, "today": 1213, "tot_dose_1": 32542, "tot_dose_2": 6637, "total_doses": 45816}}, "vaccinationDoneByTime": [{"ts": "2021-03-10T05:00:00.000Z", "timestamps": "2021-03-10T11:00:00.000Z", "label": "11:00-12:00", "count": 104, "dose_one": 69, "dose_two": 35}, {"ts": "2021-03-10T10:00:00.000Z", "timestamps": "2021-03-10T16:00:00.000Z", "label": "16:00-17:00", "count": 230, "dose_one": 127, "dose_two": 103}, {"ts": "2021-03-10T07:00:00.000Z", "timestamps": "2021-03-10T13:00:00.000Z", "label": "13:00-14:00", "count": 198, "dose_one": 108, "dose_two": 90}, {"ts": "2021-03-10T04:00:00.000Z", "timestamps": "2021-03-10T10:00:00.000Z", "label": "10:00-11:00", "count": 2, "dose_one": 0, "dose_two": 2}, {"ts": "2021-03-10T08:00:00.000Z", "timestamps": "2021-03-10T14:00:00.000Z", "label": "14:00-15:00", "count": 283, "dose_one": 160, "dose_two": 123}, {"ts": "2021-03-10T09:00:00.000Z", "timestamps": "2021-03-10T15:00:00.000Z", "label": "15:00-16:00", "count": 123, "dose_one": 58, "dose_two": 65}, {"ts": "2021-03-10T06:00:00.000Z", "timestamps": "2021-03-10T12:00:00.000Z", "label": "12:00-13:00", "count": 167, "dose_one": 107, "dose_two": 60}, {"ts": "2021-03-10T11:00:00.000Z", "timestamps": "2021-03-10T17:00:00.000Z", "label": "17:00-18:00", "count": 37, "dose_one": 20, "dose_two": 17}], "last7DaysRegistration": [], "last7DaysVaccination": [{"vaccine_date": "2021-03-03", "count": 3347, "dose_one": 3126, "dose_two": 221}, {"vaccine_date": "2021-03-04", "count": 3503, "dose_one": 3188, "dose_two": 315}, {"vaccine_date": "2021-03-05", "count": 2906, "dose_one": 2578, "dose_two": 328}, {"vaccine_date": "2021-03-06", "count": 2234, "dose_one": 1991, "dose_two": 243}, {"vaccine_date": "2021-03-08", "count": 1998, "dose_one": 1386, "dose_two": 612}, {"vaccine_date": "2021-03-09", "count": 2016, "dose_one": 1564, "dose_two": 452}], "getBeneficiariesGroupBy": [{"session_site_id": 549401, "title": "KALIYAGANJ SGH", "session_site_name": "KALIYAGANJ SGH", "total": 210, "partial_vaccinated": 61, "totally_vaccinated": 149}, {"session_site_id": 549402, "title": "Kunor BPHC", "session_site_name": "Kunor BPHC", "total": 2908, "partial_vaccinated": 2411, "totally_vaccinated": 497}, {"session_site_id": 549404, "title": "Ramganj BPHC", "session_site_name": "Ramganj BPHC", "total": 2029, "partial_vaccinated": 1530, "totally_vaccinated": 499}, {"session_site_id": 549405, "title": "Dalua RH", "session_site_name": "Dalua RH", "total": 2005, "partial_vaccinated": 1633, "totally_vaccinated": 372}, {"session_site_id": 549406, "title": "Lodhan RH", "session_site_name": "Lodhan RH", "total": 1640, "partial_vaccinated": 1442, "totally_vaccinated": 198}, {"session_site_id": 554860, "title": "Raiganj Rural Hospital", "session_site_name": "Raiganj Rural Hospital", "total": 2750, "partial_vaccinated": 2023, "totally_vaccinated": 727}, {"session_site_id": 563366, "title": "ITAHAR RURAL HOSPITAL", "session_site_name": "ITAHAR RURAL HOSPITAL", "total": 2607, "partial_vaccinated": 1943, "totally_vaccinated": 664}, {"session_site_id": 563426, "title": "HEMTABAD RURAL HOSPITAL", "session_site_name": "HEMTABAD RURAL HOSPITAL", "total": 2302, "partial_vaccinated": 1849, "totally_vaccinated": 453}, {"session_site_id": 563488, "title": "KARANDIGHI RURAL HOSPITAL", "session_site_name": "KARANDIGHI RURAL HOSPITAL", "total": 2624, "partial_vaccinated": 2170, "totally_vaccinated": 454}, {"session_site_id": 563793, "title": "CHAKULIA RURAL HOSPITAL", "session_site_name": "CHAKULIA RURAL HOSPITAL", "total": 1880, "partial_vaccinated": 1479, "totally_vaccinated": 401}, {"session_site_id": 563801, "title": "ISLAMPUR SSH", "session_site_name": "ISLAMPUR SSH", "total": 1294, "partial_vaccinated": 785, "totally_vaccinated": 509}, {"session_site_id": 563810, "title": "RAIGANJ GOVERMENT MCH", "session_site_name": "RAIGANJ GOVERMENT MCH", "total": 1886, "partial_vaccinated": 1678, "totally_vaccinated": 208}, {"session_site_id": 565797, "title": "Raiganj GMCH PPU", "session_site_name": "Raiganj GMCH PPU", "total": 1230, "partial_vaccinated": 731, "totally_vaccinated": 499}, {"session_site_id": 580860, "title": "Kasba Police Hospital", "session_site_name": "Kasba Police Hospital", "total": 2327, "partial_vaccinated": 1984, "totally_vaccinated": 343}, {"session_site_id": 580869, "title": "Raiganj UPHC 4", "session_site_name": "Raiganj UPHC 4", "total": 2242, "partial_vaccinated": 2039, "totally_vaccinated": 203}, {"session_site_id": 587997, "title": "Islampur SSH (covax)", "session_site_name": "Islampur SSH (covax)", "total": 1568, "partial_vaccinated": 1488, "totally_vaccinated": 80}, {"session_site_id": 588077, "title": "Kaliyaganj SGH (covax)", "session_site_name": "Kaliyaganj SGH (covax)", "total": 1260, "partial_vaccinated": 1258, "totally_vaccinated": 2}, {"session_site_id": 588173, "title": "Raiganj GMCH (covax)", "session_site_name": "Raiganj GMCH (covax)", "total": 788, "partial_vaccinated": 782, "totally_vaccinated": 6}, {"session_site_id": 591568, "title": "Mirual BSF Camp (covax)", "session_site_name": "Mirual BSF Camp (covax)", "total": 1362, "partial_vaccinated": 1362, "totally_vaccinated": 0}, {"session_site_id": 597458, "title": "Panjipara BSF Camp (Covax)", "session_site_name": "Panjipara BSF Camp (Covax)", "total": 1318, "partial_vaccinated": 1318, "totally_vaccinated": 0}, {"session_site_id": 607495, "title": "Marnai PHC (COVAX).", "session_site_name": "Marnai PHC (COVAX).", "total": 133, "partial_vaccinated": 133, "totally_vaccinated": 0}, {"session_site_id": 607503, "title": "Churaman PHC.", "session_site_name": "Churaman PHC.", "total": 109, "partial_vaccinated": 108, "totally_vaccinated": 1}, {"session_site_id": 607506, "title": "Surun PHC", "session_site_name": "Surun PHC", "total": 135, "partial_vaccinated": 111, "totally_vaccinated": 24}, {"session_site_id": 607508, "title": "Bangalbari PHC.", "session_site_name": "Bangalbari PHC.", "total": 118, "partial_vaccinated": 109, "totally_vaccinated": 9}, {"session_site_id": 607510, "title": "Sujali (covax).", "session_site_name": "Sujali (covax).", "total": 34, "partial_vaccinated": 34, "totally_vaccinated": 0}, {"session_site_id": 608797, "title": "Kanki PHC (covax)", "session_site_name": "Kanki PHC (covax)", "total": 85, "partial_vaccinated": 85, "totally_vaccinated": 0}, {"session_site_id": 608818, "title": "Rasakhowa PHC", "session_site_name": "Rasakhowa PHC", "total": 140, "partial_vaccinated": 132, "totally_vaccinated": 8}, {"session_site_id": 608845, "title": "Panjipara PHC (covax)", "session_site_name": "Panjipara PHC (covax)", "total": 130, "partial_vaccinated": 130, "totally_vaccinated": 0}, {"session_site_id": 608867, "title": "Dalkhola PHC (covax)", "session_site_name": "Dalkhola PHC (covax)", "total": 161, "partial_vaccinated": 161, "totally_vaccinated": 0}, {"session_site_id": 608928, "title": "Majihar PHC", "session_site_name": "Majihar PHC", "total": 76, "partial_vaccinated": 75, "totally_vaccinated": 1}, {"session_site_id": 608944, "title": "Bindole PHC", "session_site_name": "Bindole PHC", "total": 78, "partial_vaccinated": 72, "totally_vaccinated": 6}, {"session_site_id": 608974, "title": "Durgapur PHC", "session_site_name": "Durgapur PHC", "total": 171, "partial_vaccinated": 166, "totally_vaccinated": 5}, {"session_site_id": 608988, "title": "Bhatun PHC (covax)", "session_site_name": "Bhatun PHC (covax)", "total": 162, "partial_vaccinated": 162, "totally_vaccinated": 0}, {"session_site_id": 609276, "title": "Daspara PHC", "session_site_name": "Daspara PHC", "total": 200, "partial_vaccinated": 190, "totally_vaccinated": 10}, {"session_site_id": 609301, "title": "Lakhipur PHC", "session_site_name": "Lakhipur PHC", "total": 7, "partial_vaccinated": 6, "totally_vaccinated": 1}, {"session_site_id": 609349, "title": "Sonapur PHC (covax)", "session_site_name": "Sonapur PHC (covax)", "total": 79, "partial_vaccinated": 79, "totally_vaccinated": 0}, {"session_site_id": 609664, "title": "Raiganj GMCH 2", "session_site_name": "Raiganj GMCH 2", "total": 576, "partial_vaccinated": 289, "totally_vaccinated": 287}, {"session_site_id": 617510, "title": "Kismat Altapur SC", "session_site_name": "Kismat Altapur SC", "total": 9, "partial_vaccinated": 9, "totally_vaccinated": 0}, {"session_site_id": 617526, "title": "Lahutara II GPO", "session_site_name": "Lahutara II GPO", "total": 34, "partial_vaccinated": 34, "totally_vaccinated": 0}, {"session_site_id": 617836, "title": "Mudafat HWC", "session_site_name": "Mudafat HWC", "total": 119, "partial_vaccinated": 119, "totally_vaccinated": 0}, {"session_site_id": 617847, "title": "Dalimgaon HWC", "session_site_name": "Dalimgaon HWC", "total": 53, "partial_vaccinated": 53, "totally_vaccinated": 0}, {"session_site_id": 617876, "title": "Surun II GP", "session_site_name": "Surun II GP", "total": 29, "partial_vaccinated": 26, "totally_vaccinated": 3}, {"session_site_id": 617877, "title": "Gulandar II GP", "session_site_name": "Gulandar II GP", "total": 17, "partial_vaccinated": 16, "totally_vaccinated": 1}, {"session_site_id": 617886, "title": "Durgapur GP", "session_site_name": "Durgapur GP", "total": 46, "partial_vaccinated": 44, "totally_vaccinated": 2}, {"session_site_id": 617889, "title": "Chainagar GP", "session_site_name": "Chainagar GP", "total": 6, "partial_vaccinated": 6, "totally_vaccinated": 0}, {"session_site_id": 617893, "title": "Bishnupur GP", "session_site_name": "Bishnupur GP", "total": 9, "partial_vaccinated": 9, "totally_vaccinated": 0}, {"session_site_id": 617897, "title": "Dimrulla SC", "session_site_name": "Dimrulla SC", "total": 11, "partial_vaccinated": 9, "totally_vaccinated": 2}, {"session_site_id": 617902, "title": "Amaljhari SC", "session_site_name": "Amaljhari SC", "total": 20, "partial_vaccinated": 20, "totally_vaccinated": 0}, {"session_site_id": 617909, "title": "Dhanirhat HWC", "session_site_name": "Dhanirhat HWC", "total": 10, "partial_vaccinated": 8, "totally_vaccinated": 2}, {"session_site_id": 617921, "title": "Nizampur GP SC", "session_site_name": "Nizampur GP SC", "total": 13, "partial_vaccinated": 13, "totally_vaccinated": 0}, {"session_site_id": 617924, "title": "Surjapur SC", "session_site_name": "Surjapur SC", "total": 60, "partial_vaccinated": 57, "totally_vaccinated": 3}, {"session_site_id": 617925, "title": "Dehuty SC", "session_site_name": "Dehuty SC", "total": 26, "partial_vaccinated": 23, "totally_vaccinated": 3}, {"session_site_id": 617928, "title": "Panchvaya HWC", "session_site_name": "Panchvaya HWC", "total": 34, "partial_vaccinated": 30, "totally_vaccinated": 4}, {"session_site_id": 617931, "title": "Boroi HWC", "session_site_name": "Boroi HWC", "total": 6, "partial_vaccinated": 6, "totally_vaccinated": 0}, {"session_site_id": 617933, "title": "Jhitkia HWC", "session_site_name": "Jhitkia HWC", "total": 29, "partial_vaccinated": 29, "totally_vaccinated": 0}, {"session_site_id": 617935, "title": "Star Nursing Home", "session_site_name": "Star Nursing Home", "total": 8, "partial_vaccinated": 8, "totally_vaccinated": 0}, {"session_site_id": 617990, "title": "Goalpokhar SC", "session_site_name": "Goalpokhar SC", "total": 11, "partial_vaccinated": 10, "totally_vaccinated": 1}, {"session_site_id": 617992, "title": "Goti SC", "session_site_name": "Goti SC", "total": 4, "partial_vaccinated": 4, "totally_vaccinated": 0}, {"session_site_id": 617993, "title": "Goagaon I", "session_site_name": "Goagaon I", "total": 1, "partial_vaccinated": 1, "totally_vaccinated": 0}], "reportFor": "State : 36 & District: 736 | 2021-03-10", "timestamp": "2021-03-10 17:30:57"}