{"topBlock": {"sites": {"total": 45, "govt": 45, "pvt": 0, "today": null}, "sessions": {"total": 10200, "govt": 10200, "pvt": 0, "today": null}, "registration": {"total": null, "male": null, "female": null, "others": null, "today": null}, "vaccination": {"total": 57301, "male": 32841, "female": 24457, "others": 3, "covishield": 63483, "covaxin": 5127, "today": 1703, "tot_dose_1": 57301, "tot_dose_2": 11309, "total_doses": 68610, "aefi": 2}}, "vaccinationDoneByTime": [{"ts": "2021-04-03 09", "timestamps": "2021-04-03T10:00:00.000Z", "label": "09:00-10:00", "count": 12, "dose_one": 11, "dose_two": 1}, {"ts": "2021-04-03 10", "timestamps": "2021-04-03T11:00:00.000Z", "label": "10:00-11:00", "count": 217, "dose_one": 212, "dose_two": 5}, {"ts": "2021-04-03 11", "timestamps": "2021-04-03T12:00:00.000Z", "label": "11:00-12:00", "count": 403, "dose_one": 367, "dose_two": 36}, {"ts": "2021-04-03 12", "timestamps": "2021-04-03T13:00:00.000Z", "label": "12:00-13:00", "count": 509, "dose_one": 506, "dose_two": 3}, {"ts": "2021-04-03 13", "timestamps": "2021-04-03T14:00:00.000Z", "label": "13:00-14:00", "count": 295, "dose_one": 290, "dose_two": 5}, {"ts": "2021-04-03 14", "timestamps": "2021-04-03T15:00:00.000Z", "label": "14:00-15:00", "count": 156, "dose_one": 153, "dose_two": 3}, {"ts": "2021-04-03 15", "timestamps": "2021-04-03T16:00:00.000Z", "label": "15:00-16:00", "count": 55, "dose_one": 55, "dose_two": 0}, {"ts": "2021-04-03 16", "timestamps": "2021-04-03T17:00:00.000Z", "label": "16:00-17:00", "count": 37, "dose_one": 35, "dose_two": 2}, {"ts": "2021-04-03 17", "timestamps": "2021-04-03T18:00:00.000Z", "label": "17:00-18:00", "count": 18, "dose_one": 18, "dose_two": 0}, {"ts": "2021-04-03 18", "timestamps": "2021-04-03T19:00:00.000Z", "label": "18:00-19:00", "count": 7, "dose_one": 7, "dose_two": 0}, {"ts": "2021-04-03 22", "timestamps": "2021-04-03T23:00:00.000Z", "label": "22:00-23:00", "count": 1, "dose_one": 1, "dose_two": 0}], "last7DaysRegistration": [], "last7DaysVaccination": [{"vaccine_date": "2021-03-27", "count": 2455, "dose_one": 2437, "dose_two": 18, "covishield": 2438, "covaxin": 17, "aefi": 0}, {"vaccine_date": "2021-03-30", "count": 195, "dose_one": 176, "dose_two": 19, "covishield": 177, "covaxin": 18, "aefi": 0}, {"vaccine_date": "2021-03-31", "count": 1319, "dose_one": 1277, "dose_two": 42, "covishield": 1307, "covaxin": 12, "aefi": 0}, {"vaccine_date": "2021-04-01", "count": 2466, "dose_one": 2234, "dose_two": 232, "covishield": 2068, "covaxin": 398, "aefi": 0}, {"vaccine_date": "2021-04-02", "count": 2914, "dose_one": 2818, "dose_two": 96, "covishield": 2599, "covaxin": 315, "aefi": 0}], "last5daySessionStatus": [{"session_date": "2021-04-02", "total": "47", "planned": "11", "ongoing": "16", "completed": "20"}, {"session_date": "2021-03-27", "total": "46", "planned": "8", "ongoing": "23", "completed": "15"}, {"session_date": "2021-03-31", "total": "47", "planned": "11", "ongoing": "17", "completed": "19"}, {"session_date": "2021-03-28", "total": "4", "planned": "4", "ongoing": "0", "completed": "0"}, {"session_date": "2021-04-01", "total": "55", "planned": "21", "ongoing": "18", "completed": "16"}, {"session_date": "2021-03-30", "total": "13", "planned": "2", "ongoing": "5", "completed": "6"}], "getBeneficiariesGroupBy": [{"session_site_id": 562683, "title": "CHC BASHKHARI AMD", "session_site_name": "CHC BASHKHARI AMD", "total": 813, "partial_vaccinated": 573, "totally_vaccinated": 240, "today": 70}, {"session_site_id": 562750, "title": "MCH Wing District Hospital 01", "session_site_name": "MCH Wing District Hospital 01", "total": 431, "partial_vaccinated": 315, "totally_vaccinated": 116, "today": 0}, {"session_site_id": 562833, "title": "MRA Medical College 2n Dose", "session_site_name": "MRA Medical College 2n Dose", "total": 119, "partial_vaccinated": 3, "totally_vaccinated": 116, "today": 0}, {"session_site_id": 563240, "title": "MCH Wing district hosptal", "session_site_name": "MCH Wing district hosptal", "total": 213, "partial_vaccinated": 158, "totally_vaccinated": 55, "today": 0}, {"session_site_id": 563345, "title": "TANDA CHC 2", "session_site_name": "TANDA CHC 2", "total": 42, "partial_vaccinated": 8, "totally_vaccinated": 34, "today": 0}, {"session_site_id": 563681, "title": "CHC Tanda ABN", "session_site_name": "CHC Tanda ABN", "total": 2152, "partial_vaccinated": 1189, "totally_vaccinated": 963, "today": 0}, {"session_site_id": 566942, "title": "Chc Akbarpur ABN", "session_site_name": "Chc Akbarpur ABN", "total": 2786, "partial_vaccinated": 1909, "totally_vaccinated": 877, "today": 35}, {"session_site_id": 566950, "title": "Chc Akbarpur District Jail", "session_site_name": "Chc Akbarpur District Jail", "total": 590, "partial_vaccinated": 472, "totally_vaccinated": 118, "today": 0}, {"session_site_id": 566974, "title": "Chc Tanda AMD", "session_site_name": "Chc Tanda AMD", "total": 468, "partial_vaccinated": 286, "totally_vaccinated": 182, "today": 18}, {"session_site_id": 566980, "title": "Chc Tanda 3", "session_site_name": "Chc Tanda 3", "total": 370, "partial_vaccinated": 220, "totally_vaccinated": 150, "today": 0}, {"session_site_id": 567030, "title": "Chc Tanda 4", "session_site_name": "Chc Tanda 4", "total": 445, "partial_vaccinated": 325, "totally_vaccinated": 120, "today": 0}, {"session_site_id": 567042, "title": "MRA Medical college 2", "session_site_name": "MRA Medical college 2", "total": 293, "partial_vaccinated": 17, "totally_vaccinated": 276, "today": 0}, {"session_site_id": 567048, "title": "MRA Medical College 3", "session_site_name": "MRA Medical College 3", "total": 240, "partial_vaccinated": 9, "totally_vaccinated": 231, "today": 0}, {"session_site_id": 567054, "title": "MRA Medical College 4", "session_site_name": "MRA Medical College 4", "total": 152, "partial_vaccinated": 7, "totally_vaccinated": 145, "today": 0}, {"session_site_id": 567061, "title": "Chc Baskhari 2", "session_site_name": "Chc Baskhari 2", "total": 416, "partial_vaccinated": 284, "totally_vaccinated": 132, "today": 0}, {"session_site_id": 567071, "title": "Chc Bhiyaon ABN", "session_site_name": "Chc Bhiyaon ABN", "total": 1791, "partial_vaccinated": 1230, "totally_vaccinated": 561, "today": 107}, {"session_site_id": 567079, "title": "Chc Bhiyaon 2", "session_site_name": "Chc Bhiyaon 2", "total": 199, "partial_vaccinated": 124, "totally_vaccinated": 75, "today": 0}, {"session_site_id": 567102, "title": "Chc Jalalpur 1", "session_site_name": "Chc Jalalpur 1", "total": 589, "partial_vaccinated": 449, "totally_vaccinated": 140, "today": 0}, {"session_site_id": 567109, "title": "Chc Jalalpur 2", "session_site_name": "Chc Jalalpur 2", "total": 257, "partial_vaccinated": 125, "totally_vaccinated": 132, "today": 0}, {"session_site_id": 567118, "title": "Chc Jalalpur 3", "session_site_name": "Chc Jalalpur 3", "total": 186, "partial_vaccinated": 145, "totally_vaccinated": 41, "today": 0}, {"session_site_id": 567123, "title": "Chc Jalalpur 4", "session_site_name": "Chc Jalalpur 4", "total": 139, "partial_vaccinated": 78, "totally_vaccinated": 61, "today": 0}, {"session_site_id": 567407, "title": "MCH wing District Hospital2", "session_site_name": "MCH wing District Hospital2", "total": 421, "partial_vaccinated": 298, "totally_vaccinated": 123, "today": 0}, {"session_site_id": 567411, "title": "Chc Jalalpur ABN", "session_site_name": "Chc Jalalpur ABN", "total": 1735, "partial_vaccinated": 1077, "totally_vaccinated": 658, "today": 64}, {"session_site_id": 569165, "title": "MRA Medical College 1", "session_site_name": "MRA Medical College 1", "total": 196, "partial_vaccinated": 19, "totally_vaccinated": 177, "today": 0}, {"session_site_id": 571419, "title": "MJP DISTRICT HOSPITAL ABN", "session_site_name": "MJP DISTRICT HOSPITAL ABN", "total": 589, "partial_vaccinated": 291, "totally_vaccinated": 298, "today": 0}, {"session_site_id": 573942, "title": "RAMA Multispeciclty Hospital", "session_site_name": "RAMA Multispeciclty Hospital", "total": 83, "partial_vaccinated": 83, "totally_vaccinated": 0, "today": 0}, {"session_site_id": 573972, "title": "CHC BASKHARI 3", "session_site_name": "CHC BASKHARI 3", "total": 28, "partial_vaccinated": 28, "totally_vaccinated": 0, "today": 0}, {"session_site_id": 573982, "title": "CHC KATEHARI ABN", "session_site_name": "CHC KATEHARI ABN", "total": 2589, "partial_vaccinated": 1816, "totally_vaccinated": 773, "today": 59}, {"session_site_id": 573988, "title": "CHC KATEHARI 2", "session_site_name": "CHC KATEHARI 2", "total": 410, "partial_vaccinated": 274, "totally_vaccinated": 136, "today": 0}, {"session_site_id": 574014, "title": "CHC ALAPUR ABN", "session_site_name": "CHC ALAPUR ABN", "total": 2110, "partial_vaccinated": 1326, "totally_vaccinated": 784, "today": 30}, {"session_site_id": 574026, "title": "PHC RAMNAGAR ABN", "session_site_name": "PHC RAMNAGAR ABN", "total": 1245, "partial_vaccinated": 1081, "totally_vaccinated": 164, "today": 57}, {"session_site_id": 574067, "title": "CHC JAHANGIRGANJ ABN", "session_site_name": "CHC JAHANGIRGANJ ABN", "total": 2531, "partial_vaccinated": 1854, "totally_vaccinated": 677, "today": 74}, {"session_site_id": 574069, "title": "CHC JAHANGIRGANJ 2", "session_site_name": "CHC JAHANGIRGANJ 2", "total": 335, "partial_vaccinated": 212, "totally_vaccinated": 123, "today": 0}, {"session_site_id": 574117, "title": "CHC BHITI 02", "session_site_name": "CHC BHITI 02", "total": 216, "partial_vaccinated": 78, "totally_vaccinated": 138, "today": 0}, {"session_site_id": 574121, "title": "CHC BHITI 03", "session_site_name": "CHC BHITI 03", "total": 8, "partial_vaccinated": 8, "totally_vaccinated": 0, "today": 0}, {"session_site_id": 574123, "title": "CHC BHITI ABN", "session_site_name": "CHC BHITI ABN", "total": 2674, "partial_vaccinated": 2004, "totally_vaccinated": 670, "today": 28}, {"session_site_id": 579837, "title": "Aarogyam Hospital NTPC", "session_site_name": "Aarogyam Hospital NTPC", "total": 96, "partial_vaccinated": 4, "totally_vaccinated": 92, "today": 0}, {"session_site_id": 592857, "title": "CHC Baskhari ABN", "session_site_name": "CHC Baskhari ABN", "total": 1601, "partial_vaccinated": 1251, "totally_vaccinated": 350, "today": 0}, {"session_site_id": 603457, "title": "MJP DISTRICT HOSPITAL AMD", "session_site_name": "MJP DISTRICT HOSPITAL AMD", "total": 2140, "partial_vaccinated": 1739, "totally_vaccinated": 401, "today": 134}, {"session_site_id": 603465, "title": "MMR Medical College AMD", "session_site_name": "MMR Medical College AMD", "total": 1128, "partial_vaccinated": 883, "totally_vaccinated": 245, "today": 43}, {"session_site_id": 603481, "title": "RAMA MULTISPECICITY HOSP AMD", "session_site_name": "RAMA MULTISPECICITY HOSP AMD", "total": 9, "partial_vaccinated": 9, "totally_vaccinated": 0, "today": 0}, {"session_site_id": 608353, "title": "PHC UTRETHU", "session_site_name": "PHC UTRETHU", "total": 717, "partial_vaccinated": 686, "totally_vaccinated": 31, "today": 8}, {"session_site_id": 608372, "title": "PHC BRAHIMPUR KUSUMA", "session_site_name": "PHC BRAHIMPUR KUSUMA", "total": 305, "partial_vaccinated": 297, "totally_vaccinated": 8, "today": 5}, {"session_site_id": 608478, "title": "PHC BADAGOAN IBRAHIMPUR", "session_site_name": "PHC BADAGOAN IBRAHIMPUR", "total": 529, "partial_vaccinated": 516, "totally_vaccinated": 13, "today": 7}, {"session_site_id": 608591, "title": "PHC ARIAUNA", "session_site_name": "PHC ARIAUNA", "total": 562, "partial_vaccinated": 561, "totally_vaccinated": 1, "today": 21}, {"session_site_id": 608602, "title": "PHC SIKANDERPUR", "session_site_name": "PHC SIKANDERPUR", "total": 693, "partial_vaccinated": 673, "totally_vaccinated": 20, "today": 16}, {"session_site_id": 608716, "title": "UHC Mohisinpur Mansur", "session_site_name": "UHC Mohisinpur Mansur", "total": 662, "partial_vaccinated": 651, "totally_vaccinated": 11, "today": 32}, {"session_site_id": 608728, "title": "UHC PANDATOLA", "session_site_name": "UHC PANDATOLA", "total": 484, "partial_vaccinated": 471, "totally_vaccinated": 13, "today": 0}, {"session_site_id": 608941, "title": "UHP MUBARAKPUR TANDA", "session_site_name": "UHP MUBARAKPUR TANDA", "total": 509, "partial_vaccinated": 475, "totally_vaccinated": 34, "today": 35}, {"session_site_id": 613993, "title": "PHC AOWRANG NAGAR", "session_site_name": "PHC AOWRANG NAGAR", "total": 987, "partial_vaccinated": 973, "totally_vaccinated": 14, "today": 0}, {"session_site_id": 614009, "title": "PHC ASHRAFPUR BARWA", "session_site_name": "PHC ASHRAFPUR BARWA", "total": 703, "partial_vaccinated": 692, "totally_vaccinated": 11, "today": 14}, {"session_site_id": 614014, "title": "PHC NASHEERPUR", "session_site_name": "PHC NASHEERPUR", "total": 991, "partial_vaccinated": 988, "totally_vaccinated": 3, "today": 4}, {"session_site_id": 614018, "title": "PHC BEWANA", "session_site_name": "PHC BEWANA", "total": 973, "partial_vaccinated": 944, "totally_vaccinated": 29, "today": 30}, {"session_site_id": 614024, "title": "PHC JAMUNIPUR", "session_site_name": "PHC JAMUNIPUR", "total": 556, "partial_vaccinated": 552, "totally_vaccinated": 4, "today": 8}, {"session_site_id": 614026, "title": "PHC TARAKHURD", "session_site_name": "PHC TARAKHURD", "total": 958, "partial_vaccinated": 956, "totally_vaccinated": 2, "today": 14}, {"session_site_id": 614036, "title": "PHC MADERMAU", "session_site_name": "PHC MADERMAU", "total": 635, "partial_vaccinated": 631, "totally_vaccinated": 4, "today": 6}, {"session_site_id": 614042, "title": "PHC MAKRAHI", "session_site_name": "PHC MAKRAHI", "total": 785, "partial_vaccinated": 785, "totally_vaccinated": 0, "today": 1}, {"session_site_id": 614048, "title": "PHC LAKHANIPATTI", "session_site_name": "PHC LAKHANIPATTI", "total": 661, "partial_vaccinated": 657, "totally_vaccinated": 4, "today": 0}, {"session_site_id": 614072, "title": "PHC NARIYAO", "session_site_name": "PHC NARIYAO", "total": 502, "partial_vaccinated": 501, "totally_vaccinated": 1, "today": 28}, {"session_site_id": 614080, "title": "PHC KAMAHRIYAGHAT", "session_site_name": "PHC KAMAHRIYAGHAT", "total": 659, "partial_vaccinated": 656, "totally_vaccinated": 3, "today": 36}, {"session_site_id": 614086, "title": "PHC KAMALPUR PIKARPUR", "session_site_name": "PHC KAMALPUR PIKARPUR", "total": 1765, "partial_vaccinated": 1762, "totally_vaccinated": 3, "today": 122}, {"session_site_id": 614110, "title": "PHC HASWAR", "session_site_name": "PHC HASWAR", "total": 668, "partial_vaccinated": 635, "totally_vaccinated": 33, "today": 0}, {"session_site_id": 614113, "title": "PHC MUNDERA", "session_site_name": "PHC MUNDERA", "total": 1344, "partial_vaccinated": 1338, "totally_vaccinated": 6, "today": 0}, {"session_site_id": 614153, "title": "PHC BADEPUR", "session_site_name": "PHC BADEPUR", "total": 538, "partial_vaccinated": 534, "totally_vaccinated": 4, "today": 73}, {"session_site_id": 614302, "title": "PHC DHAMARUA", "session_site_name": "PHC DHAMARUA", "total": 343, "partial_vaccinated": 337, "totally_vaccinated": 6, "today": 50}, {"session_site_id": 614310, "title": "PHC KASIMPUR", "session_site_name": "PHC KASIMPUR", "total": 445, "partial_vaccinated": 444, "totally_vaccinated": 1, "today": 51}, {"session_site_id": 614315, "title": "PHC MALIPUR", "session_site_name": "PHC MALIPUR", "total": 702, "partial_vaccinated": 683, "totally_vaccinated": 19, "today": 77}, {"session_site_id": 614319, "title": "PHC Bandipur", "session_site_name": "PHC Bandipur", "total": 2246, "partial_vaccinated": 2170, "totally_vaccinated": 76, "today": 96}, {"session_site_id": 614446, "title": "PPC Tanda", "session_site_name": "PPC Tanda", "total": 377, "partial_vaccinated": 314, "totally_vaccinated": 63, "today": 12}, {"session_site_id": 614618, "title": "UPHC JALALPUR", "session_site_name": "UPHC JALALPUR", "total": 406, "partial_vaccinated": 403, "totally_vaccinated": 3, "today": 5}, {"session_site_id": 614671, "title": "MAHILA HOSPITAL JALALPUR", "session_site_name": "MAHILA HOSPITAL JALALPUR", "total": 739, "partial_vaccinated": 721, "totally_vaccinated": 18, "today": 20}, {"session_site_id": 615625, "title": "PHC SAMMANPUR", "session_site_name": "PHC SAMMANPUR", "total": 177, "partial_vaccinated": 176, "totally_vaccinated": 1, "today": 13}, {"session_site_id": 647282, "title": "HWC MAKHDOM NAGAR", "session_site_name": "HWC MAKHDOM NAGAR", "total": 240, "partial_vaccinated": 240, "totally_vaccinated": 0, "today": 0}, {"session_site_id": 647288, "title": "HWC GOHNIYA", "session_site_name": "HWC GOHNIYA", "total": 127, "partial_vaccinated": 125, "totally_vaccinated": 2, "today": 0}, {"session_site_id": 647291, "title": "HWC TENDUIKLA", "session_site_name": "HWC TENDUIKLA", "total": 351, "partial_vaccinated": 350, "totally_vaccinated": 1, "today": 13}, {"session_site_id": 647370, "title": "HWC GOVIND SAHAB", "session_site_name": "HWC GOVIND SAHAB", "total": 990, "partial_vaccinated": 987, "totally_vaccinated": 3, "today": 48}, {"session_site_id": 659031, "title": "HWC Gohniya Covaxin", "session_site_name": "HWC Gohniya Covaxin", "total": 59, "partial_vaccinated": 59, "totally_vaccinated": 0, "today": 0}, {"session_site_id": 659056, "title": "HWC MAKHDOM NAGAR Covaxin", "session_site_name": "HWC MAKHDOM NAGAR Covaxin", "total": 51, "partial_vaccinated": 51, "totally_vaccinated": 0, "today": 0}, {"session_site_id": 659303, "title": "PHC HANSWAR Covaxin", "session_site_name": "PHC HANSWAR Covaxin", "total": 102, "partial_vaccinated": 102, "totally_vaccinated": 0, "today": 38}, {"session_site_id": 659334, "title": "PHC MUNDERA Covaxin", "session_site_name": "PHC MUNDERA Covaxin", "total": 230, "partial_vaccinated": 230, "totally_vaccinated": 0, "today": 89}, {"session_site_id": 660481, "title": "HWC Songoan", "session_site_name": "HWC Songoan", "total": 144, "partial_vaccinated": 144, "totally_vaccinated": 0, "today": 12}, {"session_site_id": 660491, "title": "HWC Ariya Bazar", "session_site_name": "HWC Ariya Bazar", "total": 17, "partial_vaccinated": 16, "totally_vaccinated": 1, "today": 0}], "topUtilization": [], "verificationMethod": {"aadhaar": null, "others": null}, "reportFor": "State : 34 & District: 625 | 2021-04-03", "aefiPercentage": 0.003, "vaccinationByAge": {"total": 57301, "vac_18_25": 2104, "vac_25_40": 7330, "vac_40_60": 25605, "above_60": 22206}, "timestamp": "2021-04-03 18:04:37"}