{"topBlock": {"sites": {"total": 47, "govt": 47, "pvt": 0, "today": null}, "sessions": {"total": 4700, "govt": 4700, "pvt": 0, "today": null}, "registration": {"total": null, "male": null, "female": null, "others": null, "today": null}, "vaccination": {"total": 71275, "male": 38500, "female": 32769, "others": 6, "covishield": 78153, "covaxin": 0, "today": 2938, "tot_dose_1": 71275, "tot_dose_2": 6878, "total_doses": 78153, "aefi": 1}}, "vaccinationDoneByTime": [{"ts": "2021-04-18 09", "timestamps": "2021-04-18T10:00:00.000Z", "label": "09:00-10:00", "count": 102, "dose_one": 98, "dose_two": 4}, {"ts": "2021-04-18 10", "timestamps": "2021-04-18T11:00:00.000Z", "label": "10:00-11:00", "count": 497, "dose_one": 474, "dose_two": 23}, {"ts": "2021-04-18 11", "timestamps": "2021-04-18T12:00:00.000Z", "label": "11:00-12:00", "count": 481, "dose_one": 464, "dose_two": 17}, {"ts": "2021-04-18 12", "timestamps": "2021-04-18T13:00:00.000Z", "label": "12:00-13:00", "count": 537, "dose_one": 509, "dose_two": 28}, {"ts": "2021-04-18 13", "timestamps": "2021-04-18T14:00:00.000Z", "label": "13:00-14:00", "count": 136, "dose_one": 134, "dose_two": 2}, {"ts": "2021-04-18 14", "timestamps": "2021-04-18T15:00:00.000Z", "label": "14:00-15:00", "count": 273, "dose_one": 264, "dose_two": 9}, {"ts": "2021-04-18 15", "timestamps": "2021-04-18T16:00:00.000Z", "label": "15:00-16:00", "count": 343, "dose_one": 336, "dose_two": 7}, {"ts": "2021-04-18 16", "timestamps": "2021-04-18T17:00:00.000Z", "label": "16:00-17:00", "count": 247, "dose_one": 160, "dose_two": 87}, {"ts": "2021-04-18 17", "timestamps": "2021-04-18T18:00:00.000Z", "label": "17:00-18:00", "count": 152, "dose_one": 115, "dose_two": 37}, {"ts": "2021-04-18 18", "timestamps": "2021-04-18T19:00:00.000Z", "label": "18:00-19:00", "count": 66, "dose_one": 62, "dose_two": 4}, {"ts": "2021-04-18 19", "timestamps": "2021-04-18T20:00:00.000Z", "label": "19:00-20:00", "count": 11, "dose_one": 11, "dose_two": 0}, {"ts": "2021-04-18 20", "timestamps": "2021-04-18T21:00:00.000Z", "label": "20:00-21:00", "count": 41, "dose_one": 36, "dose_two": 5}, {"ts": "2021-04-18 21", "timestamps": "2021-04-18T22:00:00.000Z", "label": "21:00-22:00", "count": 52, "dose_one": 46, "dose_two": 6}], "last7DaysRegistration": [], "last7DaysVaccination": [{"vaccine_date": "2021-04-11", "count": 1910, "dose_one": 1875, "dose_two": 35, "covishield": 1910, "covaxin": 0, "aefi": 0}, {"vaccine_date": "2021-04-12", "count": 4249, "dose_one": 4150, "dose_two": 99, "covishield": 4249, "covaxin": 0, "aefi": 0}, {"vaccine_date": "2021-04-13", "count": 6576, "dose_one": 6457, "dose_two": 119, "covishield": 6576, "covaxin": 0, "aefi": 0}, {"vaccine_date": "2021-04-14", "count": 5777, "dose_one": 5677, "dose_two": 100, "covishield": 5777, "covaxin": 0, "aefi": 0}, {"vaccine_date": "2021-04-15", "count": 4415, "dose_one": 4297, "dose_two": 118, "covishield": 4415, "covaxin": 0, "aefi": 0}, {"vaccine_date": "2021-04-16", "count": 5591, "dose_one": 5392, "dose_two": 199, "covishield": 5591, "covaxin": 0, "aefi": 0}, {"vaccine_date": "2021-04-17", "count": 4782, "dose_one": 4590, "dose_two": 192, "covishield": 4782, "covaxin": 0, "aefi": 0}], "last5daySessionStatus": [{"session_date": "2021-04-17", "total": 38, "planned": 5, "ongoing": 22, "completed": 11}, {"session_date": "2021-04-14", "total": 32, "planned": 4, "ongoing": 16, "completed": 12}, {"session_date": "2021-04-15", "total": 34, "planned": 6, "ongoing": 13, "completed": 15}, {"session_date": "2021-04-12", "total": 33, "planned": 3, "ongoing": 14, "completed": 16}, {"session_date": "2021-04-13", "total": 32, "planned": 5, "ongoing": 14, "completed": 13}, {"session_date": "2021-04-16", "total": 34, "planned": 4, "ongoing": 20, "completed": 10}, {"session_date": "2021-04-11", "total": 28, "planned": 3, "ongoing": 11, "completed": 14}], "getBeneficiariesGroupBy": [{"state_id": 1, "state_name": "Andaman and Nicobar Islands", "district_id": 1, "id": 1, "title": "North and Middle Andaman", "district_name": "North and Middle Andaman", "total": 23010, "partial_vaccinated": 21383, "totally_vaccinated": 1627, "today": 1029}, {"state_id": 1, "state_name": "Andaman and Nicobar Islands", "district_id": 2, "id": 2, "title": "South Andaman", "district_name": "South Andaman", "total": 36136, "partial_vaccinated": 31749, "totally_vaccinated": 4387, "today": 1452}, {"state_id": 1, "state_name": "Andaman and Nicobar Islands", "district_id": 3, "id": 3, "title": "Nicobar", "district_name": "Nicobar", "total": 5764, "partial_vaccinated": 5210, "totally_vaccinated": 554, "today": 150}], "reportFor": "State : 1 | 2021-04-18", "aefiPercentage": 0.001, "vaccinationByAge": {"total": 71275, "vac_18_25": 337, "vac_25_40": 5178, "vac_40_60": 43012, "above_60": 22746}, "timestamp": "2021-04-18 18:03:16"}