{"topBlock": {"sites": {"total": 1687, "govt": 1458, "pvt": 229, "today": null}, "sessions": {"total": 228150, "govt": 199950, "pvt": 28200, "today": null}, "registration": {"total": null, "male": null, "female": null, "others": null, "today": null}, "vaccination": {"total": 2858633, "male": 1468968, "female": 1389297, "others": 368, "covishield": 2871056, "covaxin": 370276, "today": 61422, "tot_dose_1": 2858633, "tot_dose_2": 382699, "total_doses": 3241332, "aefi": 812}}, "vaccinationDoneByTime": [{"ts": "2021-04-20 08", "timestamps": "2021-04-20T09:00:00.000Z", "label": "08:00-09:00", "count": 90, "dose_one": 40, "dose_two": 50}, {"ts": "2021-04-20 09", "timestamps": "2021-04-20T10:00:00.000Z", "label": "09:00-10:00", "count": 1258, "dose_one": 598, "dose_two": 660}, {"ts": "2021-04-20 10", "timestamps": "2021-04-20T11:00:00.000Z", "label": "10:00-11:00", "count": 5452, "dose_one": 2910, "dose_two": 2542}, {"ts": "2021-04-20 11", "timestamps": "2021-04-20T12:00:00.000Z", "label": "11:00-12:00", "count": 10112, "dose_one": 6212, "dose_two": 3900}, {"ts": "2021-04-20 12", "timestamps": "2021-04-20T13:00:00.000Z", "label": "12:00-13:00", "count": 10427, "dose_one": 6711, "dose_two": 3716}, {"ts": "2021-04-20 13", "timestamps": "2021-04-20T14:00:00.000Z", "label": "13:00-14:00", "count": 8520, "dose_one": 5613, "dose_two": 2907}, {"ts": "2021-04-20 14", "timestamps": "2021-04-20T15:00:00.000Z", "label": "14:00-15:00", "count": 8225, "dose_one": 5505, "dose_two": 2720}, {"ts": "2021-04-20 15", "timestamps": "2021-04-20T16:00:00.000Z", "label": "15:00-16:00", "count": 7098, "dose_one": 4875, "dose_two": 2223}, {"ts": "2021-04-20 16", "timestamps": "2021-04-20T17:00:00.000Z", "label": "16:00-17:00", "count": 3350, "dose_one": 2433, "dose_two": 917}, {"ts": "2021-04-20 17", "timestamps": "2021-04-20T18:00:00.000Z", "label": "17:00-18:00", "count": 1348, "dose_one": 864, "dose_two": 484}, {"ts": "2021-04-20 18", "timestamps": "2021-04-20T19:00:00.000Z", "label": "18:00-19:00", "count": 1432, "dose_one": 827, "dose_two": 605}, {"ts": "2021-04-20 19", "timestamps": "2021-04-20T20:00:00.000Z", "label": "19:00-20:00", "count": 1136, "dose_one": 801, "dose_two": 335}, {"ts": "2021-04-20 20", "timestamps": "2021-04-20T21:00:00.000Z", "label": "20:00-21:00", "count": 1142, "dose_one": 852, "dose_two": 290}, {"ts": "2021-04-20 21", "timestamps": "2021-04-20T22:00:00.000Z", "label": "21:00-22:00", "count": 875, "dose_one": 576, "dose_two": 299}, {"ts": "2021-04-20 22", "timestamps": "2021-04-20T23:00:00.000Z", "label": "22:00-23:00", "count": 731, "dose_one": 531, "dose_two": 200}], "last7DaysRegistration": [], "last7DaysVaccination": [{"vaccine_date": "2021-04-13", "count": 126671, "dose_one": 108869, "dose_two": 17802, "covishield": 114164, "covaxin": 12507, "aefi": 2}, {"vaccine_date": "2021-04-14", "count": 126775, "dose_one": 103950, "dose_two": 22825, "covishield": 109196, "covaxin": 17579, "aefi": 4}, {"vaccine_date": "2021-04-15", "count": 49638, "dose_one": 36042, "dose_two": 13596, "covishield": 43434, "covaxin": 6204, "aefi": 1}, {"vaccine_date": "2021-04-16", "count": 70712, "dose_one": 50570, "dose_two": 20142, "covishield": 62547, "covaxin": 8165, "aefi": 6}, {"vaccine_date": "2021-04-17", "count": 52803, "dose_one": 37634, "dose_two": 15169, "covishield": 47252, "covaxin": 5551, "aefi": 0}, {"vaccine_date": "2021-04-18", "count": 32336, "dose_one": 25120, "dose_two": 7216, "covishield": 28079, "covaxin": 4257, "aefi": 1}, {"vaccine_date": "2021-04-19", "count": 80604, "dose_one": 50214, "dose_two": 30390, "covishield": 67560, "covaxin": 13044, "aefi": 1}], "last5daySessionStatus": [{"session_date": "2021-04-17", "total": 1247, "planned": 211, "ongoing": 588, "completed": 448}, {"session_date": "2021-04-18", "total": 1073, "planned": 426, "ongoing": 349, "completed": 298}, {"session_date": "2021-04-15", "total": 1306, "planned": 274, "ongoing": 532, "completed": 500}, {"session_date": "2021-04-16", "total": 1582, "planned": 285, "ongoing": 669, "completed": 628}, {"session_date": "2021-04-14", "total": 2058, "planned": 322, "ongoing": 841, "completed": 895}, {"session_date": "2021-04-19", "total": 1676, "planned": 262, "ongoing": 703, "completed": 711}, {"session_date": "2021-04-13", "total": 1949, "planned": 249, "ongoing": 805, "completed": 895}], "getBeneficiariesGroupBy": [{"state_id": 12, "state_name": "Haryana", "district_id": 186, "id": 186, "title": "Kurukshetra", "district_name": "Kurukshetra", "total": 93100, "partial_vaccinated": 84189, "totally_vaccinated": 8911, "today": 2776}, {"state_id": 12, "state_name": "Haryana", "district_id": 187, "id": 187, "title": "Panchkula", "district_name": "Panchkula", "total": 110289, "partial_vaccinated": 90303, "totally_vaccinated": 19986, "today": 2569}, {"state_id": 12, "state_name": "Haryana", "district_id": 188, "id": 188, "title": "Gurgaon", "district_name": "Gurgaon", "total": 386356, "partial_vaccinated": 326163, "totally_vaccinated": 60193, "today": 8439}, {"state_id": 12, "state_name": "Haryana", "district_id": 189, "id": 189, "title": "Jhajjar", "district_name": "Jhajjar", "total": 104705, "partial_vaccinated": 90868, "totally_vaccinated": 13837, "today": 1549}, {"state_id": 12, "state_name": "Haryana", "district_id": 190, "id": 190, "title": "Kaithal", "district_name": "Kaithal", "total": 78180, "partial_vaccinated": 69178, "totally_vaccinated": 9002, "today": 1363}, {"state_id": 12, "state_name": "Haryana", "district_id": 191, "id": 191, "title": "Hisar", "district_name": "Hisar", "total": 125676, "partial_vaccinated": 111479, "totally_vaccinated": 14197, "today": 2390}, {"state_id": 12, "state_name": "Haryana", "district_id": 192, "id": 192, "title": "Rohtak", "district_name": "Rohtak", "total": 96124, "partial_vaccinated": 81209, "totally_vaccinated": 14915, "today": 2159}, {"state_id": 12, "state_name": "Haryana", "district_id": 193, "id": 193, "title": "Ambala", "district_name": "Ambala", "total": 170294, "partial_vaccinated": 140076, "totally_vaccinated": 30218, "today": 4196}, {"state_id": 12, "state_name": "Haryana", "district_id": 194, "id": 194, "title": "Sirsa", "district_name": "Sirsa", "total": 154448, "partial_vaccinated": 128176, "totally_vaccinated": 26272, "today": 4921}, {"state_id": 12, "state_name": "Haryana", "district_id": 195, "id": 195, "title": "Panipat", "district_name": "Panipat", "total": 94337, "partial_vaccinated": 83824, "totally_vaccinated": 10513, "today": 3522}, {"state_id": 12, "state_name": "Haryana", "district_id": 196, "id": 196, "title": "Fatehabad", "district_name": "Fatehabad", "total": 72666, "partial_vaccinated": 64094, "totally_vaccinated": 8572, "today": 782}, {"state_id": 12, "state_name": "Haryana", "district_id": 197, "id": 197, "title": "Yamunanagar", "district_name": "Yamunanagar", "total": 136991, "partial_vaccinated": 118998, "totally_vaccinated": 17993, "today": 4547}, {"state_id": 12, "state_name": "Haryana", "district_id": 198, "id": 198, "title": "Sonipat", "district_name": "Sonipat", "total": 136491, "partial_vaccinated": 122181, "totally_vaccinated": 14310, "today": 2400}, {"state_id": 12, "state_name": "Haryana", "district_id": 199, "id": 199, "title": "Faridabad", "district_name": "Faridabad", "total": 231970, "partial_vaccinated": 200936, "totally_vaccinated": 31034, "today": 3535}, {"state_id": 12, "state_name": "Haryana", "district_id": 200, "id": 200, "title": "Bhiwani", "district_name": "Bhiwani", "total": 96715, "partial_vaccinated": 85205, "totally_vaccinated": 11510, "today": 2469}, {"state_id": 12, "state_name": "Haryana", "district_id": 201, "id": 201, "title": "Charkhi Dadri", "district_name": "Charkhi Dadri", "total": 58631, "partial_vaccinated": 53164, "totally_vaccinated": 5467, "today": 1008}, {"state_id": 12, "state_name": "Haryana", "district_id": 202, "id": 202, "title": "Rewari", "district_name": "Rewari", "total": 110068, "partial_vaccinated": 96880, "totally_vaccinated": 13188, "today": 1483}, {"state_id": 12, "state_name": "Haryana", "district_id": 203, "id": 203, "title": "Karnal", "district_name": "Karnal", "total": 166483, "partial_vaccinated": 141763, "totally_vaccinated": 24720, "today": 6179}, {"state_id": 12, "state_name": "Haryana", "district_id": 204, "id": 204, "title": "Jind", "district_name": "Jind", "total": 77439, "partial_vaccinated": 72524, "totally_vaccinated": 4915, "today": 1460}, {"state_id": 12, "state_name": "Haryana", "district_id": 205, "id": 205, "title": "Nuh", "district_name": "Nuh", "total": 27431, "partial_vaccinated": 24155, "totally_vaccinated": 3276, "today": 1003}, {"state_id": 12, "state_name": "Haryana", "district_id": 206, "id": 206, "title": "Mahendragarh", "district_name": "Mahendragarh", "total": 98518, "partial_vaccinated": 89804, "totally_vaccinated": 8714, "today": 541}, {"state_id": 12, "state_name": "Haryana", "district_id": 207, "id": 207, "title": "Palwal", "district_name": "Palwal", "total": 68617, "partial_vaccinated": 62945, "totally_vaccinated": 5672, "today": 1713}], "reportFor": "State : 12 | 2021-04-20", "aefiPercentage": 0.028, "vaccinationByAge": {"total": 2858633, "vac_18_25": 37930, "vac_25_40": 187660, "vac_40_60": 1227400, "above_60": 1404080}, "timestamp": "2021-04-20 18:03:46"}