{"topBlock": {"sites": {"total": 23, "govt": 22, "pvt": 1, "today": null}, "sessions": {"total": 2500, "govt": 2400, "pvt": 100, "today": null}, "registration": {"total": null, "male": null, "female": null, "others": null, "today": null}, "vaccination": {"total": 21289, "male": 14621, "female": 6667, "others": 1, "covishield": 26329, "covaxin": 0, "today": 1032, "tot_dose_1": 21289, "tot_dose_2": 5040, "total_doses": 26329, "aefi": 2}}, "vaccinationDoneByTime": [{"ts": "2021-03-23T08:00:00.000Z", "timestamps": "2021-03-23T14:00:00.000Z", "label": "14:00-15:00", "count": 118, "dose_one": 105, "dose_two": 13}, {"ts": "2021-03-23T11:00:00.000Z", "timestamps": "2021-03-23T17:00:00.000Z", "label": "17:00-18:00", "count": 2, "dose_one": 0, "dose_two": 2}, {"ts": "2021-03-23T06:00:00.000Z", "timestamps": "2021-03-23T12:00:00.000Z", "label": "12:00-13:00", "count": 305, "dose_one": 265, "dose_two": 40}, {"ts": "2021-03-23T14:00:00.000Z", "timestamps": "2021-03-23T20:00:00.000Z", "label": "20:00-21:00", "count": 1, "dose_one": 0, "dose_two": 1}, {"ts": "2021-03-23T04:00:00.000Z", "timestamps": "2021-03-23T10:00:00.000Z", "label": "10:00-11:00", "count": 1, "dose_one": 0, "dose_two": 1}, {"ts": "2021-03-23T15:00:00.000Z", "timestamps": "2021-03-23T21:00:00.000Z", "label": "21:00-22:00", "count": 1, "dose_one": 0, "dose_two": 1}, {"ts": "2021-03-23T05:00:00.000Z", "timestamps": "2021-03-23T11:00:00.000Z", "label": "11:00-12:00", "count": 150, "dose_one": 112, "dose_two": 38}, {"ts": "2021-03-23T09:00:00.000Z", "timestamps": "2021-03-23T15:00:00.000Z", "label": "15:00-16:00", "count": 109, "dose_one": 84, "dose_two": 25}, {"ts": "2021-03-23T03:00:00.000Z", "timestamps": "2021-03-23T09:00:00.000Z", "label": "09:00-10:00", "count": 2, "dose_one": 2, "dose_two": 0}, {"ts": "2021-03-23T10:00:00.000Z", "timestamps": "2021-03-23T16:00:00.000Z", "label": "16:00-17:00", "count": 144, "dose_one": 129, "dose_two": 15}, {"ts": "2021-03-23T12:00:00.000Z", "timestamps": "2021-03-23T18:00:00.000Z", "label": "18:00-19:00", "count": 2, "dose_one": 0, "dose_two": 2}, {"ts": "2021-03-23T07:00:00.000Z", "timestamps": "2021-03-23T13:00:00.000Z", "label": "13:00-14:00", "count": 219, "dose_one": 167, "dose_two": 52}], "last7DaysRegistration": [], "last7DaysVaccination": [{"vaccine_date": "2021-03-16", "count": 1450, "dose_one": 1127, "dose_two": 323, "covishield": 1450, "covaxin": 0, "aefi": 0}, {"vaccine_date": "2021-03-17", "count": 10, "dose_one": 10, "dose_two": 0, "covishield": 10, "covaxin": 0, "aefi": 0}, {"vaccine_date": "2021-03-18", "count": 1529, "dose_one": 1100, "dose_two": 429, "covishield": 1529, "covaxin": 0, "aefi": 0}, {"vaccine_date": "2021-03-19", "count": 1547, "dose_one": 911, "dose_two": 636, "covishield": 1547, "covaxin": 0, "aefi": 0}, {"vaccine_date": "2021-03-20", "count": 314, "dose_one": 161, "dose_two": 153, "covishield": 314, "covaxin": 0, "aefi": 0}, {"vaccine_date": "2021-03-22", "count": 1270, "dose_one": 946, "dose_two": 324, "covishield": 1270, "covaxin": 0, "aefi": 1}], "last5daySessionStatus": [{"session_date": "2021-03-16", "total": "26", "planned": "7", "ongoing": "4", "completed": "15"}, {"session_date": "2021-03-20", "total": "10", "planned": "5", "ongoing": "2", "completed": "3"}, {"session_date": "2021-03-18", "total": "26", "planned": "8", "ongoing": "4", "completed": "14"}, {"session_date": "2021-03-22", "total": "22", "planned": "4", "ongoing": "6", "completed": "12"}, {"session_date": "2021-03-19", "total": "23", "planned": "2", "ongoing": "5", "completed": "16"}], "getBeneficiariesGroupBy": [{"session_site_id": 377654, "title": "Nandpur PHC", "session_site_name": "Nandpur PHC", "total": 491, "partial_vaccinated": 455, "totally_vaccinated": 36, "today": 60}, {"session_site_id": 377658, "title": "police2 Samba ", "session_site_name": "police2 Samba ", "total": 5121, "partial_vaccinated": 4185, "totally_vaccinated": 936, "today": 172}, {"session_site_id": 386397, "title": "Bari Brahmana", "session_site_name": "Bari Brahmana", "total": 1201, "partial_vaccinated": 1079, "totally_vaccinated": 122, "today": 48}, {"session_site_id": 387563, "title": "St Joseph hosp", "session_site_name": "St Joseph hosp", "total": 92, "partial_vaccinated": 91, "totally_vaccinated": 1, "today": 0}, {"session_site_id": 387783, "title": "Bari khad NTPHC", "session_site_name": "Bari khad NTPHC", "total": 740, "partial_vaccinated": 419, "totally_vaccinated": 321, "today": 26}, {"session_site_id": 387789, "title": "Purmandal PHC", "session_site_name": "Purmandal PHC", "total": 357, "partial_vaccinated": 258, "totally_vaccinated": 99, "today": 0}, {"session_site_id": 387790, "title": "Rahya PHC", "session_site_name": "Rahya PHC", "total": 332, "partial_vaccinated": 295, "totally_vaccinated": 37, "today": 50}, {"session_site_id": 387792, "title": "Tarore NTPHC", "session_site_name": "Tarore NTPHC", "total": 336, "partial_vaccinated": 303, "totally_vaccinated": 33, "today": 30}, {"session_site_id": 387794, "title": "Gurha Salathia PHC", "session_site_name": "Gurha Salathia PHC", "total": 742, "partial_vaccinated": 545, "totally_vaccinated": 197, "today": 90}, {"session_site_id": 387802, "title": "AH Ghagwal", "session_site_name": "AH Ghagwal", "total": 2087, "partial_vaccinated": 1739, "totally_vaccinated": 348, "today": 120}, {"session_site_id": 387812, "title": "Kangwal", "session_site_name": "Kangwal", "total": 356, "partial_vaccinated": 91, "totally_vaccinated": 265, "today": 10}, {"session_site_id": 387815, "title": "Pongdour", "session_site_name": "Pongdour", "total": 474, "partial_vaccinated": 158, "totally_vaccinated": 316, "today": 0}, {"session_site_id": 387818, "title": "Sanoora PHC", "session_site_name": "Sanoora PHC", "total": 1036, "partial_vaccinated": 928, "totally_vaccinated": 108, "today": 110}, {"session_site_id": 387823, "title": "Rattanpur PHC", "session_site_name": "Rattanpur PHC", "total": 681, "partial_vaccinated": 640, "totally_vaccinated": 41, "today": 20}, {"session_site_id": 387824, "title": "Surara", "session_site_name": "Surara", "total": 170, "partial_vaccinated": 61, "totally_vaccinated": 109, "today": 0}, {"session_site_id": 387825, "title": "Daghore", "session_site_name": "Daghore", "total": 333, "partial_vaccinated": 287, "totally_vaccinated": 46, "today": 21}, {"session_site_id": 387847, "title": "EH vijapur", "session_site_name": "EH vijapur", "total": 2119, "partial_vaccinated": 1846, "totally_vaccinated": 273, "today": 86}, {"session_site_id": 387858, "title": "Rangoor", "session_site_name": "Rangoor", "total": 213, "partial_vaccinated": 37, "totally_vaccinated": 176, "today": 0}, {"session_site_id": 387859, "title": "Penthi", "session_site_name": "Penthi", "total": 93, "partial_vaccinated": 10, "totally_vaccinated": 83, "today": 0}, {"session_site_id": 387865, "title": "Sangwal", "session_site_name": "Sangwal", "total": 167, "partial_vaccinated": 0, "totally_vaccinated": 167, "today": 0}, {"session_site_id": 389047, "title": "Nud PHC", "session_site_name": "Nud PHC", "total": 647, "partial_vaccinated": 636, "totally_vaccinated": 11, "today": 49}, {"session_site_id": 389050, "title": "Sumb PHC", "session_site_name": "Sumb PHC", "total": 1323, "partial_vaccinated": 1151, "totally_vaccinated": 172, "today": 20}, {"session_site_id": 389521, "title": "Bainglarh", "session_site_name": "Bainglarh", "total": 894, "partial_vaccinated": 828, "totally_vaccinated": 66, "today": 30}, {"session_site_id": 562617, "title": "Ramgarh Community Centre", "session_site_name": "Ramgarh Community Centre", "total": 1288, "partial_vaccinated": 807, "totally_vaccinated": 481, "today": 80}, {"session_site_id": 566062, "title": "HQ Samba Nud", "session_site_name": "HQ Samba Nud", "total": 862, "partial_vaccinated": 307, "totally_vaccinated": 555, "today": 0}, {"session_site_id": 579957, "title": "kristu Jyoti hosp", "session_site_name": "kristu Jyoti hosp", "total": 14, "partial_vaccinated": 14, "totally_vaccinated": 0, "today": 0}, {"session_site_id": 580008, "title": "New Life Hospital", "session_site_name": "New Life Hospital", "total": 18, "partial_vaccinated": 18, "totally_vaccinated": 0, "today": 0}, {"session_site_id": 602867, "title": "Shree Aum Hospital", "session_site_name": "Shree Aum Hospital", "total": 242, "partial_vaccinated": 227, "totally_vaccinated": 15, "today": 10}], "topUtilization": [], "verificationMethod": {"aadhaar": null, "others": null}, "reportFor": "State : 14 & District: 236 | 2021-03-23", "aefiPercentage": 0.009, "vaccinationByAge": {"total": 21289, "vac_18_25": 374, "vac_25_40": 5150, "vac_40_60": 6095, "above_60": 9660}, "timestamp": "2021-03-23 18:01:15"}